{"bookHeader":"","bookName":"SALMOS 93","bookContent":[{"id":0,"tipo":"calling","texto":"O poder e a majestade de Deus"},{"id":1,"tipo":"versiculo","texto":"Reina o SENHOR. Revestiu-se de majestade; de poder se revestiu o SENHOR e se cingiu. Firmou o mundo, que não vacila."},{"id":2,"tipo":"versiculo","texto":"Desde a antiguidade, está firme o teu trono; tu és desde a eternidade."},{"id":3,"tipo":"versiculo","texto":"Levantam os rios, ó SENHOR, levantam os rios o seu bramido; levantam os rios o seu fragor."},{"id":4,"tipo":"versiculo","texto":"Mas o SENHOR nas alturas é mais poderoso do que o bramido das grandes águas, do que os poderosos vagalhões do mar."},{"id":5,"tipo":"versiculo","texto":"Fidelíssimos são os teus testemunhos; à tua casa convém a santidade, SENHOR, para todo o sempre."}]}