{"bookHeader":"","bookName":"SALMOS 99","bookContent":[{"id":0,"tipo":"calling","texto":"A santidade de Deus"},{"id":1,"tipo":"versiculo","texto":"Reina o SENHOR; tremam os povos. Ele está entronizado acima dos querubins; abale-se a terra."},{"id":2,"tipo":"versiculo","texto":"O SENHOR é grande em Sião e sobremodo elevado acima de todos os povos."},{"id":3,"tipo":"versiculo","texto":"Celebrem eles o teu nome grande e tremendo, porque é santo."},{"id":4,"tipo":"versiculo","texto":"És rei poderoso que ama a justiça; tu firmas a eqüidade, executas o juízo e a justiça em Jacó."},{"id":5,"tipo":"versiculo","texto":"Exaltai ao SENHOR, nosso Deus, e prostrai-vos ante o escabelo de seus pés, porque ele é santo."},{"id":6,"tipo":"versiculo","texto":"Moisés e Arão, entre os seus sacerdotes, e, Samuel, entre os que lhe invocam o nome, clamavam ao SENHOR, e ele os ouvia."},{"id":7,"tipo":"versiculo","texto":"Falava-lhes na coluna de nuvem; eles guardavam os seus mandamentos e a lei que lhes tinha dado."},{"id":8,"tipo":"versiculo","texto":"Tu lhes respondeste, ó SENHOR, nosso Deus; foste para eles Deus perdoador, ainda que tomando vingança dos seus feitos."},{"id":9,"tipo":"versiculo","texto":"Exaltai ao SENHOR, nosso Deus, e prostrai-vos ante o seu santo monte, porque santo é o SENHOR, nosso Deus."}]}